mantarix/__init__.py
mantarix/app.py
mantarix/auth/__init__.py
mantarix/auth/authorization.py
mantarix/auth/group.py
mantarix/auth/oauth_provider.py
mantarix/auth/oauth_token.py
mantarix/auth/providers/__init__.py
mantarix/auth/providers/auth0_oauth_provider.py
mantarix/auth/providers/azure_oauth_provider.py
mantarix/auth/providers/github_oauth_provider.py
mantarix/auth/providers/google_oauth_provider.py
mantarix/auth/user.py
mantarix/cli.py
mantarix/core/adaptive_control.py
mantarix/core/ads/banner.py
mantarix/core/ads/base_ad.py
mantarix/core/ads/interstitial.py
mantarix/core/ads/native.py
mantarix/core/alert_dialog.py
mantarix/core/alignment.py
mantarix/core/animated_switcher.py
mantarix/core/animation.py
mantarix/core/app_bar.py
mantarix/core/audio.py
mantarix/core/audio_recorder.py
mantarix/core/auto_complete.py
mantarix/core/autofill_group.py
mantarix/core/badge.py
mantarix/core/banner.py
mantarix/core/blur.py
mantarix/core/border.py
mantarix/core/border_radius.py
mantarix/core/bottom_app_bar.py
mantarix/core/bottom_sheet.py
mantarix/core/box.py
mantarix/core/button.py
mantarix/core/buttons.py
mantarix/core/camera.py
mantarix/core/canvas/arc.py
mantarix/core/canvas/canvas.py
mantarix/core/canvas/circle.py
mantarix/core/canvas/color.py
mantarix/core/canvas/fill.py
mantarix/core/canvas/line.py
mantarix/core/canvas/oval.py
mantarix/core/canvas/path.py
mantarix/core/canvas/points.py
mantarix/core/canvas/rect.py
mantarix/core/canvas/shadow.py
mantarix/core/canvas/shape.py
mantarix/core/canvas/text.py
mantarix/core/card.py
mantarix/core/charts/bar_chart.py
mantarix/core/charts/bar_chart_group.py
mantarix/core/charts/bar_chart_rod.py
mantarix/core/charts/bar_chart_rod_stack_item.py
mantarix/core/charts/chart_axis.py
mantarix/core/charts/chart_axis_label.py
mantarix/core/charts/chart_grid_lines.py
mantarix/core/charts/chart_point_line.py
mantarix/core/charts/chart_point_shape.py
mantarix/core/charts/line_chart.py
mantarix/core/charts/line_chart_data.py
mantarix-1.0.0.dist-info/entry_points.txt
mantarix-1.0.0.dist-info/METADATA
mantarix-1.0.0.dist-info/WHEEL
mantarix-1.0.0.dist-info/RECORD
